cytriangle/__init__.py
cytriangle/ctriangle.pxd
cytriangle/cytriangle.c
cytriangle/cytriangle.pyx
cytriangle/cytriangleio.c
cytriangle/cytriangleio.pxd
cytriangle/cytriangleio.pyx
cytriangle/cytriangle.cpython-312-x86_64-linux-gnu.so
cytriangle/cytriangleio.cpython-312-x86_64-linux-gnu.so
cytriangle-3.0.1.dist-info/METADATA
cytriangle-3.0.1.dist-info/WHEEL
cytriangle-3.0.1.dist-info/licenses/LICENSE
cytriangle-3.0.1.dist-info/RECORD
