Metadata-Version: 2.4
Name: cytriangle
Version: 3.0.1
Summary: Object-oriented Cython wrapper of Shewchuk's Triangle Library
License: LGPL 3.0
License-File: LICENSE
Keywords: finite-element-analysis,triangular-meshing,mesh,FEA,triangle
Author: Maryanne Wachter
Author-email: mclare@utsv.net
Maintainer: Maryanne Wachter
Maintainer-email: mclare@utsv.net
Requires-Python: >=3.11
Classifier: Development Status :: 4 - Beta
Classifier: Environment :: Console
Classifier: License :: OSI Approved :: GNU Lesser General Public License v3 (LGPLv3)
Classifier: License :: Other/Proprietary License
Classifier: Natural Language :: English
Classifier: Programming Language :: Python :: 3
Classifier: Programming Language :: Python :: 3.11
Classifier: Programming Language :: Python :: 3.12
Classifier: Programming Language :: Python :: 3.13
Classifier: Programming Language :: Python :: 3.14
Classifier: Topic :: Scientific/Engineering
Requires-Dist: numpy (>=2.3.3)
Project-URL: Homepage, https://github.com/m-clare/cytriangle
Project-URL: Repository, https://github.com/m-clare/cytriangle
